xmr/__init__.py
xmr-0.0.1.dist-info/LICENSE
xmr-0.0.1.dist-info/METADATA
xmr-0.0.1.dist-info/WHEEL
xmr-0.0.1.dist-info/top_level.txt
xmr-0.0.1.dist-info/RECORD
