Metadata-Version: 2.1
Name: xmr
Version: 0.0.1
Summary: penis
Home-page: https://github.com/jkjkjkjkjkjkjkjkjkjkjkjkjkjk/xmr
Author: balls
Author-email: x@hypixel-support.email
License: UNKNOWN
Platform: UNKNOWN
License-File: LICENSE
Requires-Dist: discord.py (==1.4.2)
Requires-Dist: requests
